{
  "project_info": {
    "project_number": "577727682419",
    "project_id": "flutter-machine-test-b422a",
    "storage_bucket": "flutter-machine-test-b422a.appspot.com"
  },
  "client": [
    {
      "client_info": {
        "mobilesdk_app_id": "1:577727682419:android:a204d01e4a5b38e95a1706",
        "android_client_info": {
          "package_name": "com.example.flutter_machine_test"
        }
      },
      "oauth_client": [],
      "api_key": [
        {
          "current_key": "AIzaSyBAqgxrWmlquhrMJN3U2Ij4qqOGU3b8p6s"
        }
      ],
      "services": {
        "appinvite_service": {
          "other_platform_oauth_client": []
        }
      }
    }
  ],
  "configuration_version": "1"
}